applyllm/__init__.py
applyllm/accelerators/__init__.py
applyllm/accelerators/accelerator_utils.py
applyllm/io/__init__.py
applyllm/io/objectstore_utils.py
applyllm/io/pdf_text_loader.py
applyllm/io/sqldbs_utils.py
applyllm/pipelines/__init__.py
applyllm/pipelines/builder.py
applyllm/pipelines/components.py
applyllm/pipelines/config.py
applyllm/utils/__init__.py
applyllm/utils/common.py
applyllm/utils/nlp.py
llm-examples/benchmarks/human_eval.py
llm-examples/benchmarks/human_eval_solution.py
llm-examples/setup/download_img_gen.py
llm-examples/setup/download_llms.py
llm-examples/setup/download_translator.py
llm-examples/tests/left_outer_join.py
llm-examples/tests/reg.py
applyllm-0.0.8.post1.dist-info/LICENSE
applyllm-0.0.8.post1.dist-info/METADATA
applyllm-0.0.8.post1.dist-info/WHEEL
applyllm-0.0.8.post1.dist-info/top_level.txt
applyllm-0.0.8.post1.dist-info/RECORD
